discordn/__init__.py
discordn/bot.py
discordn/client.py
discordn/command.py
discordn/embed.py
discordn/errors.py
discordn/member.py
discordn/messageable.py
discordn/snowflake.py
discordn/tasks.py
discordn/voiceclient.py
discordn-1.2.2.dist-info/LICENSE
discordn-1.2.2.dist-info/METADATA
discordn-1.2.2.dist-info/WHEEL
discordn-1.2.2.dist-info/top_level.txt
discordn-1.2.2.dist-info/zip-safe
discordn-1.2.2.dist-info/RECORD
