Metadata-Version: 2.1
Name: discordn
Version: 1.2.2
Summary: Discord N
Home-page: UNKNOWN
Author: Natalie Fearnley
Author-email: nfearnley@gmail.com
License: MIT
Project-URL: Source, https://github.com/sizedev/discordn
Project-URL: Tracker, https://github.com/sizedev/discordn/issues
Keywords: discord
Platform: any
Classifier: Programming Language :: Python :: 3.8
Classifier: Operating System :: OS Independent
Classifier: License :: OSI Approved :: MIT License
Requires-Python: >=3.8
License-File: LICENSE
Requires-Dist: discord.py (==1.5.1)
Provides-Extra: dev
Requires-Dist: flake8 (==3.8.4) ; extra == 'dev'
Requires-Dist: autopep8 (==1.5.5) ; extra == 'dev'
